{
  "multipart": [
    {
      "when": {
        "power": "0"
      },
      "apply": {
        "model": "gates:block/wireless/lamp_off"
      }
    },
    {
      "when": {
        "OR": [
          {"power":"1"},
          {"power":"2"},
          {"power":"3"},
          {"power":"4"},
          {"power":"5"},
          {"power":"6"},
          {"power":"7"},
          {"power":"8"},
          {"power":"9"},
          {"power":"10"},
          {"power":"11"},
          {"power":"12"},
          {"power":"13"},
          {"power":"14"},
          {"power":"15"}
        ]
      },
      "apply": {
        "model": "gates:block/wireless/lamp_on"
      }
    }
  ]
}